{
    "$schema": "./node_modules/@magic-works/i18n-codegen/schema.json",
    "version": 1,
    "list": [
        {
            "input": "./packages/mask/shared-ui/locales/en-US.json",
            "output": "./packages/mask/shared-ui/locales/i18n_generated",
            "parser": { "type": "i18next", "contextSeparator": "$", "pluralSeparator": "_" },
            "generator": {
                "type": "i18next/react-hooks",
                "hooks": "useMaskSharedTrans",
                "namespace": "mask",
                "trans": "MaskSharedTrans",
                "emitTS": true,
                "shouldUnescape": true
            }
        },
        {
            "input": "./packages/mask/content-script/site-adaptors/twitter.com/locales/en-US.json",
            "output": "./packages/mask/content-script/site-adaptors/twitter.com/locales/i18n_generated",
            "parser": { "type": "i18next", "contextSeparator": "$", "pluralSeparator": "_" },
            "generator": {
                "type": "i18next/react-hooks",
                "hooks": "useDO_NOT_USE_",
                "namespace": "DO_NOT_USE_",
                "trans": "DO_NOT_USE_TRANSLATOR",
                "emitTS": true,
                "shouldUnescape": true
            }
        },
        {
            "input": "./packages/shared/src/locales/en-US.json",
            "output": "./packages/shared/src/locales/i18n_generated",
            "parser": { "type": "i18next", "contextSeparator": "$", "pluralSeparator": "_" },
            "generator": {
                "type": "i18next/react-hooks",
                "hooks": "useSharedTrans",
                "namespace": "shared",
                "trans": "SharedTrans",
                "emitTS": true,
                "shouldUnescape": true
            }
        },
        {
            "input": "./packages/mask/dashboard/locales/en-US.json",
            "output": "./packages/mask/dashboard/locales/i18n_generated",
            "parser": { "type": "i18next", "contextSeparator": "$", "pluralSeparator": "_" },
            "generator": {
                "type": "i18next/react-hooks",
                "hooks": "useDashboardTrans",
                "namespace": "dashboard",
                "trans": "DashboardTrans",
                "emitTS": true,
                "shouldUnescape": true
            }
        },
        {
            "input": "./packages/plugins/RSS3/src/locales/en-US.json",
            "output": "./packages/plugins/RSS3/src/locales/i18n_generated",
            "parser": { "type": "i18next", "contextSeparator": "$", "pluralSeparator": "_" },
            "generator": {
                "type": "i18next/react-hooks",
                "hooks": "useRSS3Trans",
                "namespace": "bio.rss3",
                "trans": "RSS3Trans",
                "emitTS": true,
                "shouldUnescape": true
            }
        }
    ]
}
